instmuse/__init__.py
instmuse/constants.py
instmuse/converters.py
instmuse/generators.py
instmuse/instrument_music.py
instmuse/stringed_instrument.py
instmuse-0.1.4.dist-info/LICENSE
instmuse-0.1.4.dist-info/WHEEL
instmuse-0.1.4.dist-info/METADATA
instmuse-0.1.4.dist-info/RECORD
