Metadata-Version: 2.1
Name: instmuse
Version: 0.1.4
Summary: Physical instrument library
Home-page: https://gitlab.com/cuppajoeman/instmuse
License: GPL-3.0-only
Author: ccn
Author-email: ccn@cuppajoeman.com
Requires-Python: >=3.9,<4.0
Classifier: License :: OSI Approved :: GNU General Public License v3 (GPLv3)
Classifier: Programming Language :: Python :: 3
Classifier: Programming Language :: Python :: 3.9
Requires-Dist: numuse (>=0.1.1,<0.2.0)
Project-URL: Documentation, https://instmuse.readthedocs.io/en/latest/
Project-URL: Repository, https://gitlab.com/cuppajoeman/instmuse
